gfxcili/ili9325.cpython-37m-arm-linux-gnueabihf.so
gfxcili/ili9486.cpython-37m-arm-linux-gnueabihf.so
gfxcili-0.3.1.dist-info/LICENSE
gfxcili-0.3.1.dist-info/METADATA
gfxcili-0.3.1.dist-info/WHEEL
gfxcili-0.3.1.dist-info/top_level.txt
gfxcili-0.3.1.dist-info/RECORD
